aprsd_borat_plugin/__init__.py
aprsd_borat_plugin/aprsd_borat_plugin.py
aprsd_borat_plugin/quotes.py
aprsd_borat_plugin/conf/__init__.py
aprsd_borat_plugin/conf/main.py
aprsd_borat_plugin/conf/opts.py
aprsd_borat_plugin-0.1.1.dev1.dist-info/LICENSE
aprsd_borat_plugin-0.1.1.dev1.dist-info/METADATA
aprsd_borat_plugin-0.1.1.dev1.dist-info/WHEEL
aprsd_borat_plugin-0.1.1.dev1.dist-info/entry_points.txt
aprsd_borat_plugin-0.1.1.dev1.dist-info/pbr.json
aprsd_borat_plugin-0.1.1.dev1.dist-info/top_level.txt
aprsd_borat_plugin-0.1.1.dev1.dist-info/RECORD
