Metadata-Version: 2.1
Name: aprsd-borat-plugin
Version: 0.1.1.dev1
Summary: Borat quotes for aprsd plugin
Author: Walter A. Boring IV
Author-email: waboring@hemna.com
Classifier: Topic :: Communications :: Ham Radio
Classifier: Operating System :: POSIX :: Linux
Classifier: Programming Language :: Python
Classifier: Programming Language :: Python :: 3.7
Classifier: Programming Language :: Python :: 3.8
Classifier: Programming Language :: Python :: 3.9
License-File: LICENSE
Requires-Dist: pbr
Requires-Dist: aprsd >=3.0.0
Requires-Dist: oslo-config
